<?xml version='1.0' encoding='utf-8'?>
<annotation>
	<folder>train</folder>
	<filename>batch_11_000088.jpg</filename>
	<source>
		<database>Database</database>
	</source>
	<size>
		<width>3120</width>
		<height>4160</height>
		<depth>3</depth>
	</size>
	<segmented>0</segmented>
	<object>
		<name>Unlabeled litter</name>
		<pose>Unspecified</pose>
		<truncated>0</truncated>
		<difficult>0</difficult>
		<bndbox>
			<xmin>2774</xmin>
			<ymin>1212</ymin>
			<xmax>2833</xmax>
			<ymax>1302</ymax>
		</bndbox>
	</object>
</annotation>