<?xml version='1.0' encoding='utf-8'?>
<annotation>
	<folder>train</folder>
	<filename>batch_7_000080.JPG</filename>
	<source>
		<database>Database</database>
	</source>
	<size>
		<width>3264</width>
		<height>2448</height>
		<depth>3</depth>
	</size>
	<segmented>0</segmented>
	<object>
		<name>Aluminium foil</name>
		<pose>Unspecified</pose>
		<truncated>0</truncated>
		<difficult>0</difficult>
		<bndbox>
			<xmin>1557</xmin>
			<ymin>1714</ymin>
			<xmax>1718</xmax>
			<ymax>1978</ymax>
		</bndbox>
	</object>
	<object>
		<name>Bottle</name>
		<pose>Unspecified</pose>
		<truncated>0</truncated>
		<difficult>0</difficult>
		<bndbox>
			<xmin>2093</xmin>
			<ymin>1023</ymin>
			<xmax>2235</xmax>
			<ymax>1265</ymax>
		</bndbox>
	</object>
	<object>
		<name>Bottle cap</name>
		<pose>Unspecified</pose>
		<truncated>0</truncated>
		<difficult>0</difficult>
		<bndbox>
			<xmin>2133</xmin>
			<ymin>1232</ymin>
			<xmax>2183</xmax>
			<ymax>1266</ymax>
		</bndbox>
	</object>
	<object>
		<name>Cigarette</name>
		<pose>Unspecified</pose>
		<truncated>0</truncated>
		<difficult>0</difficult>
		<bndbox>
			<xmin>3054</xmin>
			<ymin>160</ymin>
			<xmax>3084</xmax>
			<ymax>178</ymax>
		</bndbox>
	</object>
</annotation>