<?xml version='1.0' encoding='utf-8'?>
<annotation>
	<folder>train</folder>
	<filename>batch_5_000050.JPG</filename>
	<source>
		<database>Database</database>
	</source>
	<size>
		<width>2448</width>
		<height>3264</height>
		<depth>3</depth>
	</size>
	<segmented>0</segmented>
	<object>
		<name>Carton</name>
		<pose>Unspecified</pose>
		<truncated>0</truncated>
		<difficult>0</difficult>
		<bndbox>
			<xmin>663</xmin>
			<ymin>1829</ymin>
			<xmax>1012</xmax>
			<ymax>2348</ymax>
		</bndbox>
	</object>
	<object>
		<name>Plastic bag &amp; wrapper</name>
		<pose>Unspecified</pose>
		<truncated>0</truncated>
		<difficult>0</difficult>
		<bndbox>
			<xmin>721</xmin>
			<ymin>1982</ymin>
			<xmax>866</xmax>
			<ymax>2234</ymax>
		</bndbox>
	</object>
</annotation>