<?xml version='1.0' encoding='utf-8'?>
<annotation>
	<folder>train</folder>
	<filename>batch_2_000024.JPG</filename>
	<source>
		<database>Database</database>
	</source>
	<size>
		<width>2448</width>
		<height>3264</height>
		<depth>3</depth>
	</size>
	<segmented>0</segmented>
	<object>
		<name>Bottle cap</name>
		<pose>Unspecified</pose>
		<truncated>0</truncated>
		<difficult>0</difficult>
		<bndbox>
			<xmin>450</xmin>
			<ymin>2373</ymin>
			<xmax>717</xmax>
			<ymax>2615</ymax>
		</bndbox>
	</object>
	<object>
		<name>Bottle cap</name>
		<pose>Unspecified</pose>
		<truncated>0</truncated>
		<difficult>0</difficult>
		<bndbox>
			<xmin>720</xmin>
			<ymin>1367</ymin>
			<xmax>882</xmax>
			<ymax>1470</ymax>
		</bndbox>
	</object>
	<object>
		<name>Bottle</name>
		<pose>Unspecified</pose>
		<truncated>0</truncated>
		<difficult>0</difficult>
		<bndbox>
			<xmin>1340</xmin>
			<ymin>166</ymin>
			<xmax>1942</xmax>
			<ymax>2374</ymax>
		</bndbox>
	</object>
	<object>
		<name>Bottle</name>
		<pose>Unspecified</pose>
		<truncated>0</truncated>
		<difficult>0</difficult>
		<bndbox>
			<xmin>1055</xmin>
			<ymin>1</ymin>
			<xmax>1458</xmax>
			<ymax>1616</ymax>
		</bndbox>
	</object>
</annotation>