<?xml version='1.0' encoding='utf-8'?>
<annotation>
	<folder>train</folder>
	<filename>batch_15_000041.jpg</filename>
	<source>
		<database>Database</database>
	</source>
	<size>
		<width>3024</width>
		<height>4032</height>
		<depth>3</depth>
	</size>
	<segmented>0</segmented>
	<object>
		<name>Paper</name>
		<pose>Unspecified</pose>
		<truncated>0</truncated>
		<difficult>0</difficult>
		<bndbox>
			<xmin>1027</xmin>
			<ymin>2136</ymin>
			<xmax>1413</xmax>
			<ymax>2455</ymax>
		</bndbox>
	</object>
	<object>
		<name>Cigarette</name>
		<pose>Unspecified</pose>
		<truncated>0</truncated>
		<difficult>0</difficult>
		<bndbox>
			<xmin>1799</xmin>
			<ymin>3323</ymin>
			<xmax>1861</xmax>
			<ymax>3382</ymax>
		</bndbox>
	</object>
</annotation>