<?xml version="1.0" ?>
<annotation>
	<filename>batch_10_000011.jpg</filename>
	<path>/content/drive/Shareddrives/Capstone/TACO/data/batch_10/000011.jpg</path>
	<size>
		<width>4000</width>
		<height>1824</height>
		<depth/>
	</size>
	<object>
		<name>Bottle</name>
		<pose/>
		<truncated/>
		<difficult/>
		<bndbox>
			<xmin>827</xmin>
			<xmax>984</xmax>
			<ymin>90</ymin>
			<ymax>516</ymax>
		</bndbox>
	</object>
	<object>
		<name>Bottle cap</name>
		<pose/>
		<truncated/>
		<difficult/>
		<bndbox>
			<xmin>1388</xmin>
			<xmax>1539</xmax>
			<ymin>936</ymin>
			<ymax>1013</ymax>
		</bndbox>
	</object>
	<object>
		<name>Bottle</name>
		<pose/>
		<truncated/>
		<difficult/>
		<bndbox>
			<xmin>2331</xmin>
			<xmax>2548</xmax>
			<ymin>487</ymin>
			<ymax>1021</ymax>
		</bndbox>
	</object>
	<object>
		<name>Bottle</name>
		<pose/>
		<truncated/>
		<difficult/>
		<bndbox>
			<xmin>2691</xmin>
			<xmax>2952</xmax>
			<ymin>567</ymin>
			<ymax>1187</ymax>
		</bndbox>
	</object>
</annotation>
