<annotation>
	<filename>batch_5_000015.JPG</filename>
	<path>/content/drive/Shareddrives/Capstone/TACO/data/batch_5/000015.JPG</path>
	<size>
		<width>320</width>
		<height>320</height>
		<depth />
	</size>
	<object>
		<name>Can</name>
		<pose />
		<truncated />
		<difficult />
		<bndbox>
			<xmin>124</xmin>
			<xmax>135</xmax>
			<ymin>150</ymin>
			<ymax>159</ymax>
		</bndbox>
	</object>
	<object>
		<name>Can</name>
		<pose />
		<truncated />
		<difficult />
		<bndbox>
			<xmin>147</xmin>
			<xmax>174</xmax>
			<ymin>154</ymin>
			<ymax>164</ymax>
		</bndbox>
	</object>
	<object>
		<name>Other plastic</name>
		<pose />
		<truncated />
		<difficult />
		<bndbox>
			<xmin>146</xmin>
			<xmax>175</xmax>
			<ymin>157</ymin>
			<ymax>172</ymax>
		</bndbox>
	</object>
	<object>
		<name>Carton</name>
		<pose />
		<truncated />
		<difficult />
		<bndbox>
			<xmin>225</xmin>
			<xmax>241</xmax>
			<ymin>152</ymin>
			<ymax>160</ymax>
		</bndbox>
	</object>
</annotation>