<annotation>
	<filename>batch_12_000058.jpg</filename>
	<path>/content/drive/Shareddrives/Capstone/TACO/data/batch_12/000058.jpg</path>
	<size>
		<width>320</width>
		<height>320</height>
		<depth />
	</size>
	<object>
		<name>Plastic bag &amp; wrapper</name>
		<pose />
		<truncated />
		<difficult />
		<bndbox>
			<xmin>32</xmin>
			<xmax>130</xmax>
			<ymin>118</ymin>
			<ymax>162</ymax>
		</bndbox>
	</object>
	<object>
		<name>Plastic bag &amp; wrapper</name>
		<pose />
		<truncated />
		<difficult />
		<bndbox>
			<xmin>163</xmin>
			<xmax>177</xmax>
			<ymin>300</ymin>
			<ymax>311</ymax>
		</bndbox>
	</object>
	<object>
		<name>Carton</name>
		<pose />
		<truncated />
		<difficult />
		<bndbox>
			<xmin>107</xmin>
			<xmax>124</xmax>
			<ymin>267</ymin>
			<ymax>276</ymax>
		</bndbox>
	</object>
</annotation>