<annotation>
	<filename>Glass689.jpg</filename>
	<path>/content/drive/Shareddrives/Capstone/KAGGLE_DATASET/Images_of_Waste/YOLO_imgs/Glass689.jpg</path>
	<size>
		<width>320</width>
		<height>320</height>
		<depth />
	</size>
	<object>
		<name>Bottle</name>
		<pose />
		<truncated />
		<difficult />
		<bndbox>
			<xmin>171</xmin>
			<xmax>244</xmax>
			<ymin>189</ymin>
			<ymax>225</ymax>
		</bndbox>
	</object>
	<object>
		<name>Bottle</name>
		<pose />
		<truncated />
		<difficult />
		<bndbox>
			<xmin>190</xmin>
			<xmax>241</xmax>
			<ymin>64</ymin>
			<ymax>78</ymax>
		</bndbox>
	</object>
	<object>
		<name>Bottle</name>
		<pose />
		<truncated />
		<difficult />
		<bndbox>
			<xmin>78</xmin>
			<xmax>113</xmax>
			<ymin>12</ymin>
			<ymax>39</ymax>
		</bndbox>
	</object>
</annotation>